medpos/__init__.py
medpos/crfpp/__init__.py
medpos/crfpp/crftools.py
medpos/crfpp/evals.py
medpos/crfpp/loaddata.py
medpos/crfpp/tagger.py
medpos/crfpp/train.py
medpos/crfpp/nlptext_lite/__init__.py
medpos/crfpp/nlptext_lite/base.py
medpos/crfpp/nlptext_lite/corpus.py
medpos/crfpp/nlptext_lite/folder.py
medpos/crfpp/nlptext_lite/sentence.py
medpos/crfpp/nlptext_lite/text.py
medpos/crfpp/nlptext_lite/token.py
medpos/crfpp/nlptext_lite/sources/CharInfos.p
medpos/crfpp/nlptext_lite/sources/CharPinyin.p
medpos/crfpp/nlptext_lite/sources/CharRadical.p
medpos/crfpp/nlptext_lite/sources/CharStroke.p
medpos/crfpp/nlptext_lite/sources/CharSubComp.p
medpos/crfpp/nlptext_lite/sources/WordPhoneme.p
medpos/crfpp/nlptext_lite/utils/__init__.py
medpos/crfpp/nlptext_lite/utils/anno.py
medpos/crfpp/nlptext_lite/utils/channel.py
medpos/crfpp/nlptext_lite/utils/infrastructure.py
medpos/crfpp/nlptext_lite/utils/pyramid.py
medpos/crfpp/nlptext_lite/utils/vocab.py
medpos/model/MedPos/char/T_b-n1t1-f1_m-n1t1-f1_r-n1t1-f1_P-bio_E-bio/model
medpos/model/MedPos/char/T_b-n1t1-f1_m-n1t1-f1_r-n1t1-f1_P-bio_E-bio/para.p
medpos/model/MedPos/char/T_b-n1t1-f1_m-n1t1-f1_r-n1t1-f1_P-bio_E-bio/template
medpos-0.0.0.2.dist-info/LICENSE
medpos-0.0.0.2.dist-info/METADATA
medpos-0.0.0.2.dist-info/WHEEL
medpos-0.0.0.2.dist-info/top_level.txt
medpos-0.0.0.2.dist-info/RECORD
